ssb_datafangst_person_fagfunksjoner/__init__.py
ssb_datafangst_person_fagfunksjoner/functions.py
ssb_datafangst_person_fagfunksjoner/py.typed
ssb_datafangst_person_fagfunksjoner-0.0.3.dist-info/LICENSE
ssb_datafangst_person_fagfunksjoner-0.0.3.dist-info/METADATA
ssb_datafangst_person_fagfunksjoner-0.0.3.dist-info/WHEEL
ssb_datafangst_person_fagfunksjoner-0.0.3.dist-info/entry_points.txt
ssb_datafangst_person_fagfunksjoner-0.0.3.dist-info/RECORD
