Metadata-Version: 2.3
Name: ssb-datafangst-person-fagfunksjoner
Version: 0.0.3
Summary: SSB Datafangst Person Fagfunksjoner
License: MIT
Author: Elise ALstad
Author-email: lal@ssb.no
Requires-Python: >=3.10,<4.0
Classifier: Development Status :: 3 - Alpha
Classifier: License :: OSI Approved :: MIT License
Classifier: Programming Language :: Python :: 3
Classifier: Programming Language :: Python :: 3.10
Classifier: Programming Language :: Python :: 3.11
Classifier: Programming Language :: Python :: 3.12
Classifier: Programming Language :: Python :: 3.13
Requires-Dist: click (>=8.0.1)
Requires-Dist: dapla-toolbelt (>=3.0.2,<4.0.0)
Requires-Dist: ipykernel (>=6.29.5,<7.0.0)
Requires-Dist: nox (>=2024.10.9,<2025.0.0)
Requires-Dist: pandas (>=2.2.3,<3.0.0)
Requires-Dist: pandas-stubs (>=2.2.3.241009,<3.0.0.0)
Requires-Dist: polars (>=1.14.0,<2.0.0)
Requires-Dist: pyarrow (>=18.0.0,<19.0.0)
Project-URL: Changelog, https://github.com/statisticsnorway/ssb-datafangst-person-fagfunksjoner/releases
Project-URL: Documentation, https://statisticsnorway.github.io/ssb-datafangst-person-fagfunksjoner
Project-URL: Homepage, https://github.com/statisticsnorway/ssb-datafangst-person-fagfunksjoner
Project-URL: Repository, https://github.com/statisticsnorway/ssb-datafangst-person-fagfunksjoner
